[
  {
    "id": "admin_001",
    "name": "陈涛",
    "photo": "photos/chen_tao.jpg",
    "shortSummary": "青年男中音，兰州大剧院演出艺术家。",
    "bio": "兰州大剧院青年男中音，中国传统文化促进会青年歌唱家学术委员会委员，\r\n甘肃省音乐家协会会员，中Sin国际音乐比赛新加坡总决赛评委，毕业于兰州大学艺术学院音乐表演专业。现师从于四川音乐学院男中音歌唱家郭江滨副教授，先后师从于兰州大学石大勇副教授、天津音乐学院青年教师男高音歌唱家杨博老师。\r\n参演歌剧《茶花女》(并在剧中饰演男爵barone)，《波西米亚人》(并在剧中饰演军官)、《乡村骑士》、《图兰朵》(饰演传令官)、《卡门》、中央音乐学院原创联套歌剧《山海经·奔月》、兰州大剧院原创民族歌剧《西风烈》(饰演蒋英超)，以及贝多芬《第九(合唱)交响曲》终曲《欢乐颂》，马勒《第八交响曲》，马勒《第二交响曲》，福雷《安魂曲》;国家大剧院2018年国际性专题音乐会、2019年深圳“一带一路”国际音乐节开幕式音乐会。2019年兰州市新年音乐会、2019年武威市新年音乐会。中央电视台《经典咏流传》第季特别节目--《回到延安 共唱经典》“5.23音乐节”开幕式音乐会;中华人民共和国成立70周年大型音乐舞蹈史诗《奋斗吧 中华儿女》，李海交响组曲《六梠由颂》，谭盾《敦煌·慈悲颂》、叶小纲大型声乐套曲《英雄颂》、张千一交响合唱《南梁颂》，邹野交响合唱《空海》，清唱剧《上海上海》等。在交响诗《苏武》中担任苏武领唱，并多次在《黄河大合唱》中担任“黄河对口曲”张老三的领唱。\r\n获奖情况:\r\n2025年获“青歌新人”称号\r\n甘肃省第三届、第四届声乐大赛美声唱法青年组三等奖。\r\n第十届、十一届、十五届金钟奖甘肃赛区美声唱法三等奖。\r\n甘肃省首届“思路之星我的舞台梦”美声唱法大学组第一名。",
    "achievements": [],
    "roles": [
      {
        "department": "管理部",
        "position": "创始人",
        "order": 1
      },
      {
        "department": "声乐组",
        "position": "声乐教师",
        "order": 14
      }
    ]
  },
  {
    "id": "admin_002",
    "name": "苏海鹏",
    "photo": "photos/su_haipeng.jpg",
    "shortSummary": "兰州市润德艺术学校创始人。",
    "bio": "兰州市润德艺术学校创始人，兰州市安宁区民办教育协会理事、甘肃地区打\r\n击乐协会会员，从事音乐类艺考教学12年有余，培养学生近3000余人，教学管理经验丰富，管理理念先进。对待教学工作始终秉承“严格管理、科学教学”的理念。视唱练耳教学能力突出，不满足于以往经验，多次赴西安、北京、上海等地学习先进教育教学理念和管理模式。",
    "achievements": [],
    "roles": [
      {
        "department": "管理部",
        "position": "创始人",
        "order": 2
      },
      {
        "department": "理论组",
        "position": "视唱练耳教师",
        "order": 66
      }
    ]
  },
  {
    "id": "admin_003",
    "name": "王玉",
    "photo": "photos/wang_yu.jpg",
    "shortSummary": "校长，视唱练耳教师。",
    "bio": "毕业于兰州城市学院，师从萧昱副教授学习至今。于2017年从事视唱练耳教学工作至今，在工作中深受学生喜爱，工作态度认真负责。热爱教育事业，始终坚信“收获教育之果实，享受教育之甘甜”这一崇高事业之本。在校期间担任兰州城市学院Fusion合唱团负责人，2018年4月跟随甘肃省歌剧院交响乐团参与大型交响乐《梦回敦煌》的排练并赴银川演出;2018年12月在毕业实习汇报表演《歌剧魅影》中饰演魅影一角。",
    "achievements": [],
    "roles": [
      {
        "department": "管理部",
        "position": "校长",
        "order": 3
      },
      {
        "department": "理论组",
        "position": "视唱练耳教师",
        "order": 67
      }
    ]
  },
  {
    "id": "dance_001",
    "name": "韩刚",
    "photo": "photos/han_gang.jpg",
    "shortSummary": "舞蹈部校长。",
    "bio": "2019年兰州理工大学《百年弦歌·逐梦致远》百年校庆大型文艺晚会担任执行导演，2020年庆祝东乡族自治县成立70周年开幕式《逐梦东乡》担任执行导演，2021年临夏州庆祝中国共产党成立100周年大型文艺晚会《为了人民》担任执行导演与策划。获奖作品:2006年参加全国少数民族文艺汇演《那山那水那云》荣获金奖，2007年全国首届回族舞蹈大赛舞蹈《口盖碗心舒坦》荣获金奖，2010年全国少数民族体育运动会编排裕固族舞蹈《顶杠子》荣获表演银奖，2012年全国少数民族传统体育运动会编排比赛项目《花儿》表演金奖，2019年西部五省区藏族舞蹈展演编排独舞《巴郎鼓》作品银奖。\r\n",
    "achievements": [],
    "roles": [
      {
        "department": "管理部",
        "position": "舞蹈部校长",
        "order": 4
      },
      {
        "department": "舞蹈部",
        "position": "舞蹈教师",
        "order": 76
      }
    ]
  },
  {
    "id": "dance_002",
    "name": "李甜",
    "photo": "photos/li_tian.jpg",
    "shortSummary": "舞蹈部执行校长。",
    "bio": "2006年9月参加第三届全国少数民族文艺汇演。2006年9月参与大型民族舞蹈《那山那水 那云》。2012年在北京参加第四届全国少数民族文艺汇演本团创作演出的大型民族歌舞剧《民族之舟·大爱之曲》荣获创作金奖等10项，获得全国个人新人奖。2014年参加省民运会锅庄舞蹈比赛获表演一等奖。2015年12月参聼暮全省优秀剧目展演我团选送的《绚丽甘肃》荣获优秀奖。2016年7月赴北京参加第五届全国少数民族文艺会演开幕式。2016年参加国务院举办的感知中国，美国西部行。\r\n",
    "achievements": [],
    "roles": [
      {
        "department": "管理部",
        "position": "舞蹈部执行校长",
        "order": 5
      },
      {
        "department": "舞蹈部",
        "position": "舞蹈教师",
        "order": 77
      }
    ]
  },
  {
    "id": "dance_003",
    "name": "秦淼娜",
    "photo": "photos/qin_miaona.jpg",
    "shortSummary": "舞蹈部教学主管。",
    "bio": "2014年参加甘肃省小桃李杯《月狐吟》单双三金奖，2014年参加甘肃省小桃李杯《风酥雨忆》群舞银奖，2016年参加中央电视台红军长征胜利80周年演出，2016年赴人民大会堂参加第五届全国少数民族文艺汇演，2016年参加国务院举办动巡演十四个地州市及天祝、东乡、肃北蒙古族自治县县庆演出，2021年参加甘肃省庆祝中国共产党成立100周年文艺晚会《各族儿女心向党》，2021年赴人民大会堂参加第六届全国少数民族文艺会演开幕式文艺演出。\r\n",
    "achievements": [],
    "roles": [
      {
        "department": "管理部",
        "position": "舞蹈部教学主管",
        "order": 6
      },
      {
        "department": "舞蹈部",
        "position": "舞蹈教师",
        "order": 78
      }
    ]
  },
  {
    "id": "admin_004",
    "name": "祁军霞",
    "photo": "photos/qi_junxia.jpg",
    "shortSummary": "财务总监。",
    "bio": "中共党员,音乐学学士学位,从事艺考培训工作八年有余,具有高度的工作热情和丰富独特的教学经验，责任心强;有较强的综合能力，曾参与编著《高考基本乐理冲刺试卷》;所教授学生成绩优异，深受学生们喜欢和业界一致好评!大学期间学习声乐和理论作曲专业;曾获奖项:《四季花儿》作品荣获甘肃省第五届大学生展演一等奖;《红楼梦音乐作品》荣获甘肃省第五届大学生展演一等奖。",
    "achievements": [],
    "roles": [
      {
        "department": "管理部",
        "position": "财务总监",
        "order": 7
      },
      {
        "department": "理论组",
        "position": "乐理教师",
        "order": 68
      }
    ]
  },
  {
    "id": "admin_005",
    "name": "景想东",
    "photo": "photos/jing_xiangdong.jpg",
    "shortSummary": "财务主管。",
    "bio": "长期从事学校财务和后勤保障管理工作，始终秉承“服务师生、无私奉献”的宗旨，以师生满意、家长放心为工作目标。在平凡辛苦的后勤管理实践中，始终充满热情，不辱使命。",
    "achievements": [],
    "roles": [
      {
        "department": "管理部",
        "position": "财务主管",
        "order": 8
      }
    ]
  },
  {
    "id": "admin_006",
    "name": "苏海震",
    "photo": "photos/su_haizhen.jpg",
    "shortSummary": "后勤主管。",
    "bio": "长期从事学校后勤保障工作，为人耿直，热情奔放，关爱学生，任劳任怨、扎实肯干，为实现更加优质、高效、便利的后勤服务而不懈努力。",
    "achievements": [],
    "roles": [
      {
        "department": "管理部",
        "position": "后勤主管",
        "order": 9
      }
    ]
  },
  {
    "id": "vocal_001",
    "name": "杜吉刚",
    "photo": "photos/du_jigang.jpg",
    "shortSummary": "著名华裔男高音歌唱家。",
    "bio": "杰出的华裔著名男高音歌唱家，原中国文化部特聘声乐专家!中央歌剧院主要演员，澳大利亚悉尼歌剧院客座主要演员，中国青年歌唱家学术委员会艺术顾问，原天津音乐学院外聘声乐专家，声乐教授，硕士生导师，曾担任天津音乐学院声乐系副主任，中央电视台\"青歌赛\"评委，文化部\"文华奖\"评委，中国文联\"金钟奖\"评委!杜吉刚一九七九年考入中国人民解放军艺术学院音乐系，一九八三年以优异的成绩毕业，同年调入解放军第二炮兵文工团担任独唱演员，一九八七年考入中央音乐学院声乐系干部进修班，一九八八调入中央歌剧院担任主要演员，一九九零年获央视第四届青歌赛专业组第二名，一九九二年有文化部指派赴美国旧金山参加有旧金山歌剧院歌剧举办的(太平洋之声)歌剧培训班!受到歌剧大师冯时达德和玛里琳霍恩的高度赞扬!一九九二年获首届歌王歌后挑战者奖!一九九三年受中国文化部指派代表中国参加法国第四届法国马赛国际歌剧比赛获得第二名，二零零二年赴意大利随意大利著名女高音歌唱家玛拉斯宾娜进修声乐收获满满并受到大师的高度赞扬!杜吉刚的歌剧生涯起步于中央歌剧院，期间得到前苏联莫斯科大剧院的世界著名剧导演安西莫夫大师的指导，为其在歌剧表演的舞台上打下了很好基础!曾先后与中国中央歌剧院，澳大利亚亚悉尼歌剧院，德国撒布禄肯歌剧院，美国夏威夷歌剧院，新西兰基督城歌剧院合作主演了多部歌剧，还与诸多著名指挥家交响乐团合作演出大量的音乐会和独唱会音乐会以及国家的各种庆典音乐会，演出足迹遍及世界各地!并受到观众的欢迎以及同行们的认可!对于杜吉刚的演唱，澳大利亚歌剧报评论到，\"他激动人心的演唱，以及娴熟的歌唱技巧，足以使他在竞争激烈的国际歌剧舞台上自豪的昂首挺立!\"\r\n",
    "achievements": [],
    "roles": [
      {
        "department": "声乐组",
        "position": "顾问",
        "order": 10
      }
    ]
  },
  {
    "id": "vocal_002",
    "name": "郭江滨",
    "photo": "photos/guo_jiangbin.jpg",
    "shortSummary": "男中音歌唱家。",
    "bio": "男中音歌唱家，中国传统文化促进会高级文化艺术顾问，中国青年歌唱家学术委员会副主任，四川音乐学院声乐副教授，文化和旅游部艺术人才中心全国展演专家评审，青歌飞扬艺术文化品牌联合创始人，\"丝绸之路\"中俄文化交流大使，受聘俄罗斯国立师范大学特聘声乐专家，美国中西部大学特聘声乐硕导，河北经贸大学，广州大学，长江大学，宁夏大学，湖北工程学院，兰州文理学院，渭南师范学院，四川传媒学院，宁夏师范学院，汉口学院，四川电影电视学院，洛阳市声乐协会等单位特聘教授及顾问。曾获得2013圣彼得堡国际声乐大赛第一名；第十九届意大利国际青年歌唱家大赛第二名；第二届中国音乐国际大赛第一名；第三十九届意大利贝里尼国际声乐大赛中国区二等奖等国内外十余项重大赛事奖项，同时担任：俄罗斯\"什托科洛夫Shtokolov\"国际声乐大赛，意大利\"费拉拉Ferrara\"国际声乐比赛，俄罗斯\"普罗柯菲耶夫Prokofiev\"国际音乐比赛，圣彼得堡欧亚国际音乐大赛，日本东京国际声乐大赛，俄罗斯夏季艺术峰会，留声机国际音乐比赛，美国演奏家国际音乐比赛，德国威斯巴登国际音乐比赛，第五十六届意大利威尔第国际声乐比赛中国赛区执行主任，韩国国际音乐大赛，新加坡中新国际音乐大赛，香港国际声乐公开赛等赛事评审。曾受邀联合国教科文组织赴美国，新西兰，日本，新加坡，俄罗斯等国家参加各类音乐会演出。学生多人次荣获包括意大利，奥地利，德国，日本，俄罗斯，韩国，新加坡等国际奖项五十余项，获省市区院校级专业荣誉百余项。荣获\"优秀指导教师\"称号及奖励百余次，入选中国文化艺术人才库音乐类一级并获得中国诚信(音乐舞蹈)艺术人物称号。\r\n",
    "achievements": [],
    "roles": [
      {
        "department": "声乐组",
        "position": "声乐总监",
        "order": 11
      }
    ]
  },
  {
    "id": "vocal_003",
    "name": "石大勇",
    "photo": "photos/shi_dayong.jpg",
    "shortSummary": "男高音。",
    "bio": "男高音，硕士，兰州大学艺术学院音乐系声乐教师。先后师从于朱东生教授，陈虎教授，项亮教授。曾留学奥地利维也纳舒伯特音乐学院(Franz Schubert KonservatoriumWien)，布雷纳音乐学院(Prayner Konservatorium Wien)主攻美声唱法和德奥艺术歌曲(Lied)，师从于维也纳国立音乐与表演艺术大学(Univer- sitaet fur Musik und darstellende Kunst Wien)声歌系主任，奥地利当代著名男高音歌唱家，著名声乐教育家弗朗茨。卢卡索夫斯基教授(Prof.FranzLu- kasovsky)；并有幸得到我国著名声乐教育家，中央乐团声乐指导，著名男高音歌唱家吴其辉教授多年来的精心培养以及著名男中音歌唱家，声乐教育家，中央音乐学院赵登营教授的悉心指导。近年内多次指导学生在中国音乐金钟奖甘肃赛区总决赛，甘肃省第三届声乐比赛等省内外大赛中获得了优异成绩，在兰州大学成立110周年之际，于兰州大学本部大礼堂成功举办了\"庆祝兰州大学成立110周年-石大勇本科教学十年师生音乐会\".",
    "achievements": [],
    "roles": [
      {
        "department": "声乐组",
        "position": "特聘教师",
        "order": 12
      }
    ]
  },
  {
    "id": "vocal_004",
    "name": "尹胜麟",
    "photo": "photos/yin_shenglin.jpg",
    "shortSummary": "博士。",
    "bio": "博士，男高音。西北民族大学音乐学院副教授，硕士生导师，艺术实践教研室主任，泰国马希隆大学特聘博士生导师。本科-西安音乐学院音乐表演专业(导师：羊为君，廖剑斌，鲜于越歌)，硕士-意大利费拉拉国立音乐学院，博士(PHD)-波兰肖邦音乐大学。获奖：第八届，第十一届中国音乐金钟奖甘肃赛区一等奖等十余项国内外声乐类赛事奖项，基本揽获甘肃省所有声乐类重要赛事一等奖。",
    "achievements": [],
    "roles": [
      {
        "department": "声乐组",
        "position": "特聘教师",
        "order": 13
      }
    ]
  },
  {
    "id": "vocal_005",
    "name": "王举全",
    "photo": "photos/wang_juquan.jpg",
    "shortSummary": "声乐教师。",
    "bio": "毕业于西北民大音乐学院。从事声乐艺考工作23年。教学认真，经验丰富，多年来为全国各大音乐院校输送了众多优秀的声乐人才。2012年任教于甘肃省张掖市肃南职教中心。从事初，高中音乐教学。任教期间，所教学生共获县级至国家级奖项六十多项。2010年7月，学生兰鹏程荣获青春中国全国声乐总决赛少年组一等奖，并获全国教师节优秀节目评比金奖。黄仁毛荣获青春中国全国声乐总决赛少年组二等奖。",
    "achievements": [],
    "roles": [
      {
        "department": "声乐组",
        "position": "声乐教师",
        "order": 15
      }
    ]
  },
  {
    "id": "vocal_006",
    "name": "孙淼",
    "photo": "photos/sun_miao.jpg",
    "shortSummary": "女高音。",
    "bio": "女高音，硕士研究生学历。甘肃省歌剧院青年演员。甘肃省音乐家协会会员，甘肃省戏剧家协会会员。大学先后师从于萧昱教授，韦亦珺教授，上海音乐学院比利时籍女高音歌唱家，博士生导师陈其莲教授学习美声唱法声乐演唱及舞台表演。获奖情况：荣获甘肃省\"青春中国\"美声唱法一等奖。荣获\"一带一路国际艺术展演及第五届香港国际音乐节\"，甘肃赛区青年B组美声唱法二等奖。",
    "achievements": [],
    "roles": [
      {
        "department": "声乐组",
        "position": "声乐教师",
        "order": 16
      }
    ]
  },
  {
    "id": "vocal_007",
    "name": "陈璞",
    "photo": "photos/chen_pudong.jpg",
    "shortSummary": "男高音。",
    "bio": "男高音，声乐博士，文旅部中国青年歌唱家学术委员会委员，四川省音乐家协会会员，宁夏合唱协会固原分会副秘书长，曾就职于宁夏师范大学。荣获日本东京国际声乐比赛一等奖；普罗科菲耶夫音乐比赛二等奖；世界音乐文化之镜中的圣彼得堡国际音乐比赛第一名；新加坡中新国际声乐比赛第一名；俄罗斯欧亚国际声乐大赛获古典美声组第二名；\"丝绸之路\"中俄国际音乐比赛第三名等多个国内外赛事奖项；参与编导舞台剧《红军粉的故事》获第六届全国大学生艺术展演一等奖。并多次荣获省市级\"优秀指导教师\"称号，并成功入选中国文化艺术人才库音乐类二级。\r\n",
    "achievements": [],
    "roles": [
      {
        "department": "声乐组",
        "position": "声乐教师",
        "order": 17
      }
    ]
  },
  {
    "id": "vocal_008",
    "name": "马熙媛",
    "photo": "photos/ma_xiyuan.jpg",
    "shortSummary": "音乐剧演员。",
    "bio": "中国音乐剧演员，内地歌手，甘肃省歌剧院音乐剧演员，主要方向音乐剧，流行音乐。甘肃省音乐家协会会员。兰州星艺关爱特殊儿童志愿服务队特教老师。出演过多部音乐剧，发行过20余首原创作品，在各大榜单名列前茅。代表作：国家艺术基金项目音乐剧《风花雪月》饰演女一号，北京艺术基金项目音乐剧《京谣》饰演女二号。艺术歌曲代表作品：《永远的相知》《吸引》《星光灿烂》《大女生》《曾经》《夏日塔拉》《西北姑娘》《假如我们不曾相遇》《我们都要好好的》《甘肃麻辣烫》《丝路情缘》《星星的眼睛》等。中欧国际音乐节国际优秀指导老师。《中国好声音》甘肃赛区评委导师。《新声请指教》甘肃赛区评委导师。《我要出唱片》甘肃赛区评委导师。河南卫视感动人物主题曲演唱者。上海同济大学 校歌演唱者等。",
    "achievements": [],
    "roles": [
      {
        "department": "声乐组",
        "position": "流行教师",
        "order": 18
      }
    ]
  },
  {
    "id": "vocal_009",
    "name": "赵兴财",
    "photo": "photos/zhao_xingcai.jpg",
    "shortSummary": "男高音。",
    "bio": "男高音，甘肃省音乐家协会会员，青年歌唱家协会会员。本科师从于师从于兰州城市学院林岩副教授及天津音乐学院青年教师，男高音歌唱家杨博，现师从于中央音乐学院博导男高音歌唱家王传越学习美声唱法至今。2017年进入兰州音乐厅合唱团工作至今，期间参演歌剧《波西米亚人》，《乡村骑士》，《图兰朵》，《卡门》，中央音乐学院原创联套歌剧《山海经。奔月》，《茶花女》，以及贝多芬《第九(合唱)交响曲》终曲《欢乐颂》，马勒《第八交响曲》，马勒《第二交响曲》，福雷《安魂曲》；国家大剧院2018年国际性专题音乐会，2019年深圳\"一带一路\"国际音乐节开幕式音乐会。2019年兰州市新年音乐会，2019年武威市新年音乐会。中央电视台《经典咏流传》第二季特别节目《回到延安 共唱经典》\"5.23音乐节\"开幕式音乐会，李海鹰交响组曲《六祖颂》，谭盾《敦煌。慈悲颂》，叶小纲大型声乐套曲《英雄颂》，张千一交响合唱《南梁颂》，邹野交响合唱《空海》，清唱剧《上海上海》等。",
    "achievements": [],
    "roles": [
      {
        "department": "声乐组",
        "position": "声乐教师",
        "order": 19
      }
    ]
  },
  {
    "id": "vocal_010",
    "name": "吴彬",
    "photo": "photos/wu_bin.jpg",
    "shortSummary": "男高音。",
    "bio": "中国金融音乐家协会会员，兰州音乐厅合唱团男高音，第四届中国民族声乐敦煌奖西南赛区三等奖，四川电视台汶川地震三周年感恩大型演出，四川电视台建党九十周年文艺演出，2018年参加全国民族演出进步示范区\"中华一家同心共筑中国梦，不忘初心谱写华章\"改革开放四十周年大型文艺汇演，参加第十七届环青海湖国际公路自行车比赛闭幕式演出。",
    "achievements": [],
    "roles": [
      {
        "department": "声乐组",
        "position": "声乐教师",
        "order": 20
      }
    ]
  },
  {
    "id": "vocal_011",
    "name": "于伟",
    "photo": "photos/yu_wei.jpg",
    "shortSummary": "声乐教师。",
    "bio": "硕士研究生学历，2017年5月考入兰州音乐厅合唱团，先后参加了兰州音乐厅歌剧《图兰朵》，《乡村骑士》，《卡门》，《茶花女》，以及中央音乐学院原创歌剧《山海经。奔月》的排练和演出，2019年9月赴北京人民大会堂参与中华人民共和国成立70周年《奋斗吧，中华儿女》主题晚会的排练和演出，曾获第十届中国音乐金钟奖甘肃赛区三等奖。",
    "achievements": [],
    "roles": [
      {
        "department": "声乐组",
        "position": "声乐教师",
        "order": 21
      }
    ]
  },
  {
    "id": "vocal_012",
    "name": "刘鹏",
    "photo": "photos/liu_peng.jpg",
    "shortSummary": "声乐教师。",
    "bio": "中共党员，2017年毕业于兰州财经大学，师从青年男中音纪秀杰，同年考入兰州音乐厅合唱团至今，在团期间参演歌剧《波西米亚人》，《图兰朵》，《茶花女》，《卡门》，《乡村骑士》，《奔月》参演2019大型音乐舞蹈史诗《奋斗吧中华儿女》，随团参加《敦煌慈悲颂》巡演，参演兰州大剧院原创交响合唱《南梁颂》等。",
    "achievements": [],
    "roles": [
      {
        "department": "声乐组",
        "position": "声乐教师",
        "order": 22
      }
    ]
  },
  {
    "id": "vocal_013",
    "name": "张铂",
    "photo": "photos/zhang_bo.jpg",
    "shortSummary": "男中音。",
    "bio": "兰州大剧院男中音，甘肃省音乐家协会会员，西北师范大学音乐学院合唱团声乐指导；先后参加并成功演出了歌剧《波西米亚人》，《乡村骑士》音乐会版；贝多芬第九(合唱)交响曲终曲《欢乐颂》，歌剧《图兰朵》，《卡门》，《茶花女》舞台版。中央音乐学院首部大型原创歌剧《山海经。奔月》；杭州国际音乐节闭幕音乐会暨杭州爱乐乐团2018-2019音乐季音乐会《马勒第八交响曲》；2019年参加北京人民大会堂庆祝中华人民共和国成立70周年音乐舞蹈史诗《奋斗吧中华儿女》文艺晚会；2021年9月兰州大剧院《南梁颂》国家大剧院首演；谭盾大师《敦煌。慈悲颂》澳门，北京，上海等地巡演；中国爱乐乐团《空海》日本东京，京都演出等均获得巨大成功。教学方面：2021年何佳龄以甘肃省联考第六名考入四川大学；2020年张博考入西北师范大学；2021年吴槐，吕瑶以全省89名考入烟台大学；2025年包银娟取得全省18名；张琦源取得沈阳音乐学院合格证。",
    "achievements": [],
    "roles": [
      {
        "department": "声乐组",
        "position": "声乐教师",
        "order": 23
      }
    ]
  },
  {
    "id": "vocal_014",
    "name": "童倩影",
    "photo": "photos/tong_qianying.jpg",
    "shortSummary": "女高音。",
    "bio": "抒情女高音，本科毕业于四川音乐学院歌剧系，现于俄罗斯国立师范大学攻读硕士学位。\r\n2020年第五届\"央音\"全国青少年艺术展演四川省总展演金奖2021年普罗菲斯耶夫国际音乐大赛亚太地区决赛铜奖\r\n2022年俄罗斯留声机国际音乐比赛声乐类美声唱法成人组\"评审团特别奖\"荣誉称号\r\n2022年新加坡中Sin国际音乐比赛女生歌剧组冠军\r\n2023文化和旅游部人才中心全国声乐展演优秀展演者奖\r\n2023年中国青年歌唱家学术委员会青歌飞扬一青年歌唱家培养计划最佳展演者\r\n2023年美国演奏家国际音乐比赛中国赛区二等奖\r\n2024年新加坡中Sin国际音乐大赛专业开放作品组冠军\r\n2024年中国青年歌唱家学术委员会青歌飞扬一青年歌唱家培养计划业务考核选拔展演\"青歌新秀\".",
    "achievements": [],
    "roles": [
      {
        "department": "声乐组",
        "position": "声乐教师",
        "order": 24
      }
    ]
  },
  {
    "id": "vocal_015",
    "name": "黄子俊",
    "photo": "photos/huang_zijun.jpg",
    "shortSummary": "男中音。",
    "bio": "青年抒情男中音，本科毕业于四川音乐学院歌剧系，硕士就读于俄罗斯国立师范大学。\r\n2025年俄罗斯\"Ao6poBAeHe\"民歌节特邀嘉宾\r\n2025年俄罗斯\"中ecTMBanb\"AManorn HeBckmx 6eperoB\"音乐节特邀嘉宾\r\n2024年新加坡中Sin国际音乐大赛(国际赛区)美声开放组冠军\r\n2024年中国音乐小金钟全国声乐展演(美声组)四川选拔\"巴蜀新人\"称号2022年文化和旅游部人才中心全国音乐总展演\"最佳展演奖\"2022年普罗科菲耶夫国际音乐大赛亚太区声乐专业院校组银奖",
    "achievements": [],
    "roles": [
      {
        "department": "声乐组",
        "position": "声乐教师",
        "order": 25
      }
    ]
  },
  {
    "id": "vocal_016",
    "name": "柯夏",
    "photo": "photos/ke_xia.jpg",
    "shortSummary": "女高音。",
    "bio": "青年抒情女高音，本科毕业于四川音乐学院歌剧系，硕士就读于俄罗斯国立师范大学。\r\n2024年新加坡第18届中Sin国际音乐比赛歌剧组第一名；\r\n2023文化和旅游部\"这，就是我们的旋律\"音乐之旅展演活动优秀展演者；\r\n2023年中国青年歌唱家学术委员会青歌飞扬青年歌唱家培养计划活动\"最佳展演者\"\r\n2022年俄罗斯留声机国际声乐比赛声乐类美声唱法成人组\"评审团特别奖\"\r\n2020年第五届\"央音\"全国青少年艺术展演四川省总展演金奖；",
    "achievements": [],
    "roles": [
      {
        "department": "声乐组",
        "position": "声乐教师",
        "order": 26
      }
    ]
  },
  {
    "id": "vocal_017",
    "name": "刘恩骏",
    "photo": "photos/liu_enjun.jpg",
    "shortSummary": "流行教师。",
    "bio": "甘肃文旅局签约艺人，进修于天津现代音乐学院(师从现代音乐与戏剧学院流行声乐副教授王超).国家级荣誉：荣获中国第十五届金钟奖一等奖。中国音乐界最高荣誉之省级赛事佳绩：百事最强音甘肃赛区第一名；中国青春影像甘肃赛区：第一届第三名，第二届第一名。独唱音乐会。精通演唱技巧，能同时驾驭古典美声与流行唱法两大领域，曾成功举办多场拥有视唱练耳及音乐理论第一专业，教学经验丰富。教学成果突出：所带学生在艺术联考，特长生艺考，中考中均取得优异成绩，多人在各类音乐赛事中表现亮眼。\r\n",
    "achievements": [],
    "roles": [
      {
        "department": "声乐组",
        "position": "流行教师",
        "order": 27
      }
    ]
  },
  {
    "id": "vocal_018",
    "name": "李缘园",
    "photo": "photos/li_yuanyuan.jpg",
    "shortSummary": "声乐教师。",
    "bio": "李缘园声乐教师。",
    "achievements": [],
    "roles": [
      {
        "department": "声乐组",
        "position": "声乐教师",
        "order": 28
      }
    ]
  },
  {
    "id": "vocal_019",
    "name": "张婧",
    "photo": "photos/zhang_jing.jpg",
    "shortSummary": "女高音。",
    "bio": "张婧声乐教师。",
    "achievements": [],
    "roles": [
      {
        "department": "声乐组",
        "position": "声乐教师",
        "order": 29
      }
    ]
  },
  {
    "id": "vocal_020",
    "name": "台璐鑫",
    "photo": "photos/tai_luxin.jpg",
    "shortSummary": "女高音。",
    "bio": "台璐鑫声乐教师。",
    "achievements": [],
    "roles": [
      {
        "department": "声乐组",
        "position": "声乐教师",
        "order": 30
      }
    ]
  },
  {
    "id": "vocal_021",
    "name": "王盼",
    "photo": "photos/wang_pan.jpg",
    "shortSummary": "副教授。",
    "bio": "王盼声乐教师。",
    "achievements": [],
    "roles": [
      {
        "department": "声乐组",
        "position": "声乐教师",
        "order": 31
      }
    ]
  },
  {
    "id": "vocal_022",
    "name": "张涛",
    "photo": "photos/zhang_tao.jpg",
    "shortSummary": "男中音。",
    "bio": "张涛声乐教师。",
    "achievements": [],
    "roles": [
      {
        "department": "声乐组",
        "position": "声乐教师",
        "order": 32
      }
    ]
  },
  {
    "id": "instrumental_001",
    "name": "魏旭东",
    "photo": "photos/wei_xudong.jpg",
    "shortSummary": "指挥。",
    "bio": "魏旭东器乐总监。",
    "achievements": [],
    "roles": [
      {
        "department": "器乐组",
        "position": "器乐总监",
        "order": 32
      }
    ]
  },
  {
    "id": "instrumental_002",
    "name": "管民",
    "photo": "photos/guan_min.jpg",
    "shortSummary": "二胡教师。",
    "bio": "管民二胡教师。",
    "achievements": [],
    "roles": [
      {
        "department": "器乐组",
        "position": "二胡名师",
        "order": 33
      }
    ]
  },
  {
    "id": "instrumental_003",
    "name": "阚鹏",
    "photo": "photos/kan_peng.jpg",
    "shortSummary": "竹笛教师。",
    "bio": "阚鹏竹笛教师。",
    "achievements": [],
    "roles": [
      {
        "department": "器乐组",
        "position": "竹笛名师",
        "order": 34
      }
    ]
  },
  {
    "id": "instrumental_004",
    "name": "王瑞玺",
    "photo": "photos/wang_ruixi.jpg",
    "shortSummary": "萨克斯教师。",
    "bio": "王瑞玺萨克斯教师。",
    "achievements": [],
    "roles": [
      {
        "department": "器乐组",
        "position": "萨克斯名师",
        "order": 35
      }
    ]
  },
  {
    "id": "instrumental_005",
    "name": "陈劲",
    "photo": "photos/chen_jing.jpg",
    "shortSummary": "键盘教师。",
    "bio": "陈劲双排键钢琴教师。",
    "achievements": [],
    "roles": [
      {
        "department": "器乐组",
        "position": "双排键/钢琴教师",
        "order": 36
      }
    ]
  },
  {
    "id": "instrumental_006",
    "name": "宋景坤",
    "photo": "photos/song_jingkun.jpg",
    "shortSummary": "唢呐教师。",
    "bio": "宋景坤唢呐管子教师。",
    "achievements": [],
    "roles": [
      {
        "department": "器乐组",
        "position": "唢呐/管子教师",
        "order": 37
      }
    ]
  },
  {
    "id": "instrumental_007",
    "name": "张伟超",
    "photo": "photos/zhang_weichao.jpg",
    "shortSummary": "笙教师。",
    "bio": "张伟超笙教师。",
    "achievements": [],
    "roles": [
      {
        "department": "器乐组",
        "position": "笙教师",
        "order": 38
      }
    ]
  },
  {
    "id": "instrumental_008",
    "name": "肖雪",
    "photo": "photos/xiao_xue.jpg",
    "shortSummary": "小提琴教师。",
    "bio": "肖雪小提琴教师。",
    "achievements": [],
    "roles": [
      {
        "department": "器乐组",
        "position": "小提琴教师",
        "order": 53
      }
    ]
  },
  {
    "id": "哈文泽",
    "name": "哈文泽",
    "photo": "photos/placeholder.jpg",
    "shortSummary": "",
    "bio": "",
    "achievements": [],
    "roles": [
      {
        "department": "器乐组",
        "position": "笙教师",
        "order": 39
      }
    ]
  },
  {
    "id": "instrumental_009",
    "name": "陈昱铭",
    "photo": "photos/chen_yuming.jpg",
    "shortSummary": "打击乐教师。",
    "bio": "陈昱铭打击乐教师。",
    "achievements": [],
    "roles": [
      {
        "department": "器乐组",
        "position": "打击乐教师",
        "order": 54
      }
    ]
  },
  {
    "id": "王哲宇",
    "name": "王哲宇",
    "photo": "photos/placeholder.jpg",
    "shortSummary": "",
    "bio": "",
    "achievements": [],
    "roles": [
      {
        "department": "器乐组",
        "position": "钢琴教师",
        "order": 40
      }
    ]
  },
  {
    "id": "instrumental_010",
    "name": "郑钰",
    "photo": "photos/zheng_yu.jpg",
    "shortSummary": "键盘教师。",
    "bio": "郑钰钢琴低音提琴教师。",
    "achievements": [],
    "roles": [
      {
        "department": "器乐组",
        "position": "钢琴/低音提琴教师",
        "order": 56
      }
    ]
  },
  {
    "id": "何佳蔚",
    "name": "何佳蔚",
    "photo": "photos/placeholder.jpg",
    "shortSummary": "",
    "bio": "",
    "achievements": [],
    "roles": [
      {
        "department": "器乐组",
        "position": "古筝教师",
        "order": 41
      }
    ]
  },
  {
    "id": "梁军",
    "name": "梁军",
    "photo": "photos/placeholder.jpg",
    "shortSummary": "",
    "bio": "",
    "achievements": [],
    "roles": [
      {
        "department": "器乐组",
        "position": "吉他教师",
        "order": 42
      }
    ]
  },
  {
    "id": "董爌",
    "name": "董爌",
    "photo": "photos/placeholder.jpg",
    "shortSummary": "",
    "bio": "",
    "achievements": [],
    "roles": [
      {
        "department": "器乐组",
        "position": "电吉他教师",
        "order": 43
      }
    ]
  },
  {
    "id": "王淳",
    "name": "王淳",
    "photo": "photos/placeholder.jpg",
    "shortSummary": "",
    "bio": "",
    "achievements": [],
    "roles": [
      {
        "department": "器乐组",
        "position": "琵琶教师",
        "order": 44
      }
    ]
  },
  {
    "id": "王雪燕",
    "name": "王雪燕",
    "photo": "photos/placeholder.jpg",
    "shortSummary": "",
    "bio": "",
    "achievements": [],
    "roles": [
      {
        "department": "器乐组",
        "position": "扬琴教师",
        "order": 45
      }
    ]
  },
  {
    "id": "赵天星",
    "name": "赵天星",
    "photo": "photos/placeholder.jpg",
    "shortSummary": "",
    "bio": "",
    "achievements": [],
    "roles": [
      {
        "department": "器乐组",
        "position": "打击乐教师",
        "order": 46
      }
    ]
  },
  {
    "id": "李明涛",
    "name": "李明涛",
    "photo": "photos/placeholder.jpg",
    "shortSummary": "",
    "bio": "",
    "achievements": [],
    "roles": [
      {
        "department": "器乐组",
        "position": "唢呐教师",
        "order": 47
      }
    ]
  },
  {
    "id": "杨文君",
    "name": "杨文君",
    "photo": "photos/placeholder.jpg",
    "shortSummary": "",
    "bio": "",
    "achievements": [],
    "roles": [
      {
        "department": "器乐组",
        "position": "打击乐教师",
        "order": 48
      }
    ]
  },
  {
    "id": "王旭星",
    "name": "王旭星",
    "photo": "photos/placeholder.jpg",
    "shortSummary": "",
    "bio": "",
    "achievements": [],
    "roles": [
      {
        "department": "器乐组",
        "position": "竹笛教师",
        "order": 49
      }
    ]
  },
  {
    "id": "张安青",
    "name": "张安青",
    "photo": "photos/placeholder.jpg",
    "shortSummary": "",
    "bio": "",
    "achievements": [],
    "roles": [
      {
        "department": "器乐组",
        "position": "钢琴教师",
        "order": 50
      }
    ]
  },
  {
    "id": "张婷",
    "name": "张婷",
    "photo": "photos/placeholder.jpg",
    "shortSummary": "",
    "bio": "",
    "achievements": [],
    "roles": [
      {
        "department": "器乐组",
        "position": "钢琴教师",
        "order": 51
      }
    ]
  },
  {
    "id": "周意斐",
    "name": "周意斐",
    "photo": "photos/placeholder.jpg",
    "shortSummary": "",
    "bio": "",
    "achievements": [],
    "roles": [
      {
        "department": "器乐组",
        "position": "长笛教师",
        "order": 52
      }
    ]
  },
  {
    "id": "年峥",
    "name": "年峥",
    "photo": "photos/placeholder.jpg",
    "shortSummary": "",
    "bio": "",
    "achievements": [],
    "roles": [
      {
        "department": "器乐组",
        "position": "长号教师",
        "order": 57
      }
    ]
  },
  {
    "id": "陈晟",
    "name": "陈晟",
    "photo": "photos/placeholder.jpg",
    "shortSummary": "",
    "bio": "",
    "achievements": [],
    "roles": [
      {
        "department": "器乐组",
        "position": "小号教师",
        "order": 55
      }
    ]
  },
  {
    "id": "田娅蓉",
    "name": "田娅蓉",
    "photo": "photos/placeholder.jpg",
    "shortSummary": "",
    "bio": "",
    "achievements": [],
    "roles": [
      {
        "department": "器乐组",
        "position": "竖琴教师",
        "order": 59
      }
    ]
  },
  {
    "id": "王露",
    "name": "王露",
    "photo": "photos/placeholder.jpg",
    "shortSummary": "",
    "bio": "",
    "achievements": [],
    "roles": [
      {
        "department": "器乐组",
        "position": "大提琴教师",
        "order": 58
      }
    ]
  },
  {
    "id": "王乙涵",
    "name": "王乙涵",
    "photo": "photos/placeholder.jpg",
    "shortSummary": "",
    "bio": "",
    "achievements": [],
    "roles": [
      {
        "department": "器乐组",
        "position": "打击乐教师",
        "order": 60
      }
    ]
  },
  {
    "id": "顾兴涛",
    "name": "顾兴涛",
    "photo": "photos/placeholder.jpg",
    "shortSummary": "",
    "bio": "",
    "achievements": [],
    "roles": [
      {
        "department": "器乐组",
        "position": "上低音号教师",
        "order": 61
      }
    ]
  },
  {
    "id": "肖晨",
    "name": "肖晨",
    "photo": "photos/placeholder.jpg",
    "shortSummary": "",
    "bio": "",
    "achievements": [],
    "roles": [
      {
        "department": "器乐组",
        "position": "巴松管教师",
        "order": 62
      }
    ]
  },
  {
    "id": "赵嘉玮",
    "name": "赵嘉玮",
    "photo": "photos/placeholder.jpg",
    "shortSummary": "",
    "bio": "",
    "achievements": [],
    "roles": [
      {
        "department": "器乐组",
        "position": "圆号教师",
        "order": 63
      }
    ]
  },
  {
    "id": "李文辉",
    "name": "李文辉",
    "photo": "photos/placeholder.jpg",
    "shortSummary": "",
    "bio": "",
    "achievements": [],
    "roles": [
      {
        "department": "器乐组",
        "position": "竹笛教师",
        "order": 64
      }
    ]
  },
  {
    "id": "乔文华",
    "name": "乔文华",
    "photo": "photos/placeholder.jpg",
    "shortSummary": "",
    "bio": "",
    "achievements": [],
    "roles": [
      {
        "department": "理论组",
        "position": "乐理教师",
        "order": 69
      }
    ]
  },
  {
    "id": "徐倩",
    "name": "徐倩",
    "photo": "photos/placeholder.jpg",
    "shortSummary": "",
    "bio": "",
    "achievements": [],
    "roles": [
      {
        "department": "理论组",
        "position": "视唱练耳教师",
        "order": 70
      }
    ]
  },
  {
    "id": "叶国强",
    "name": "叶国强",
    "photo": "photos/placeholder.jpg",
    "shortSummary": "",
    "bio": "",
    "achievements": [],
    "roles": [
      {
        "department": "理论组",
        "position": "视唱练耳教师",
        "order": 71
      }
    ]
  },
  {
    "id": "臧天宇",
    "name": "臧天宇",
    "photo": "photos/20260119_083208_3AE3828B-B049-46DB-850D-13BE5CF083C8_1_105_c.jpeg",
    "shortSummary": "",
    "bio": "毕业于西北师范大学音乐学院音乐表演专业，师从青年男高音者通副教授。大学期间，担任学院“音为有你”新媒体工作室负责人，统筹音乐类内容策划与传播；同时为学院合唱团、MIX-CHORE泛音人声乐团核心成员，长期参与团体声乐排练与演出。\r\n\r\n在校期间，积极投身高规格艺术实践与赛事活动：2019年9月，担任共青团甘肃省委等单位联合举办的“我与祖国共奋进”青春红歌会领唱；2020年6月，策划并出任校园星歌声大赛西北师大赛区首席执行官，推动赛事圆满落地，且晋级西赛区八强。\r\n\r\n同年起，多次携手专业艺术院团登上舞台：联袂上海爱乐乐团、兰州交响乐团等，参演张艺执棒的《马勒第二交响曲》，以及李心草执棒的《贝多芬第九（合唱）交响曲》；在中国音乐家协会2020金钟之星“一带一路”民族音乐会上，与吕继宏、迪里拜尔等知名歌唱家同台献艺。2021年9月，随团登上国家大剧院舞台，参演由张千一、屈塬创作、李心草指挥的大型交响合唱组曲《南梁颂》，深刻感悟红色音乐作品的艺术内涵。\r\n\r\n专业能力上，兼顾声乐表演、音乐制作与教学创新：热爱流行演唱，能精准驾驭不同曲风的情感表达；熟练掌握录音混音全流程，可独立完成音乐作品的录制与后期制作。在教学领域，积极探索科技与教育的融合，自主开发3款基于AIGC的智能教学工具，有效优化教学流程、提升教学效率。",
    "achievements": [],
    "roles": [
      {
        "department": "理论组",
        "position": "视唱练耳教师",
        "order": 72
      }
    ]
  },
  {
    "id": "钱昇",
    "name": "钱昇",
    "photo": "photos/placeholder.jpg",
    "shortSummary": "",
    "bio": "",
    "achievements": [],
    "roles": [
      {
        "department": "理论组",
        "position": "视唱练耳教师",
        "order": 73
      }
    ]
  },
  {
    "id": "宋小龙",
    "name": "宋小龙",
    "photo": "photos/placeholder.jpg",
    "shortSummary": "",
    "bio": "",
    "achievements": [],
    "roles": [
      {
        "department": "理论组",
        "position": "视唱练耳教师",
        "order": 74
      }
    ]
  },
  {
    "id": "李艳霞",
    "name": "李艳霞",
    "photo": "photos/placeholder.jpg",
    "shortSummary": "",
    "bio": "",
    "achievements": [],
    "roles": [
      {
        "department": "理论组",
        "position": "视唱练耳教师",
        "order": 75
      }
    ]
  },
  {
    "id": "李龙",
    "name": "李龙",
    "photo": "photos/placeholder.jpg",
    "shortSummary": "",
    "bio": "",
    "achievements": [],
    "roles": [
      {
        "department": "舞蹈部",
        "position": "舞蹈教师",
        "order": 79
      }
    ]
  },
  {
    "id": "杨怡然",
    "name": "杨怡然",
    "photo": "photos/placeholder.jpg",
    "shortSummary": "",
    "bio": "",
    "achievements": [],
    "roles": [
      {
        "department": "舞蹈部",
        "position": "舞蹈教师",
        "order": 80
      }
    ]
  },
  {
    "id": "訾陈",
    "name": "訾陈",
    "photo": "photos/placeholder.jpg",
    "shortSummary": "",
    "bio": "",
    "achievements": [],
    "roles": [
      {
        "department": "舞蹈部",
        "position": "舞蹈教师",
        "order": 81
      }
    ]
  },
  {
    "id": "韩佳芮",
    "name": "韩佳芮",
    "photo": "photos/placeholder.jpg",
    "shortSummary": "",
    "bio": "",
    "achievements": [],
    "roles": [
      {
        "department": "舞蹈部",
        "position": "舞蹈教师",
        "order": 82
      }
    ]
  },
  {
    "id": "杨晓洁",
    "name": "杨晓洁",
    "photo": "photos/placeholder.jpg",
    "shortSummary": "",
    "bio": "",
    "achievements": [],
    "roles": [
      {
        "department": "舞蹈部",
        "position": "舞蹈教师",
        "order": 83
      }
    ]
  },
  {
    "id": "周文涛",
    "name": "周文涛",
    "photo": "photos/placeholder.jpg",
    "shortSummary": "",
    "bio": "",
    "achievements": [],
    "roles": [
      {
        "department": "舞蹈部",
        "position": "舞蹈教师",
        "order": 84
      }
    ]
  },
  {
    "id": "艾哲宇",
    "name": "艾哲宇",
    "photo": "photos/placeholder.jpg",
    "shortSummary": "",
    "bio": "",
    "achievements": [],
    "roles": [
      {
        "department": "舞蹈部",
        "position": "舞蹈教师",
        "order": 85
      }
    ]
  },
  {
    "id": "李慧芳",
    "name": "李慧芳",
    "photo": "photos/placeholder.jpg",
    "shortSummary": "",
    "bio": "",
    "achievements": [],
    "roles": [
      {
        "department": "舞蹈部",
        "position": "舞蹈教师",
        "order": 86
      }
    ]
  }
]
